README.md
setup.cfg
setup.py
/workspace/Prototypes/pytorch3d/pytorch3d/csrc/ext.cpp
/workspace/Prototypes/pytorch3d/pytorch3d/csrc/blending/sigmoid_alpha_blend.cu
/workspace/Prototypes/pytorch3d/pytorch3d/csrc/blending/sigmoid_alpha_blend_cpu.cpp
/workspace/Prototypes/pytorch3d/pytorch3d/csrc/compositing/alpha_composite.cu
/workspace/Prototypes/pytorch3d/pytorch3d/csrc/compositing/alpha_composite_cpu.cpp
/workspace/Prototypes/pytorch3d/pytorch3d/csrc/compositing/norm_weighted_sum.cu
/workspace/Prototypes/pytorch3d/pytorch3d/csrc/compositing/norm_weighted_sum_cpu.cpp
/workspace/Prototypes/pytorch3d/pytorch3d/csrc/compositing/weighted_sum.cu
/workspace/Prototypes/pytorch3d/pytorch3d/csrc/compositing/weighted_sum_cpu.cpp
/workspace/Prototypes/pytorch3d/pytorch3d/csrc/face_areas_normals/face_areas_normals.cu
/workspace/Prototypes/pytorch3d/pytorch3d/csrc/face_areas_normals/face_areas_normals_cpu.cpp
/workspace/Prototypes/pytorch3d/pytorch3d/csrc/gather_scatter/gather_scatter.cu
/workspace/Prototypes/pytorch3d/pytorch3d/csrc/gather_scatter/gather_scatter_cpu.cpp
/workspace/Prototypes/pytorch3d/pytorch3d/csrc/interp_face_attrs/interp_face_attrs.cu
/workspace/Prototypes/pytorch3d/pytorch3d/csrc/knn/knn.cu
/workspace/Prototypes/pytorch3d/pytorch3d/csrc/knn/knn_cpu.cpp
/workspace/Prototypes/pytorch3d/pytorch3d/csrc/packed_to_padded_tensor/packed_to_padded_tensor.cu
/workspace/Prototypes/pytorch3d/pytorch3d/csrc/packed_to_padded_tensor/packed_to_padded_tensor_cpu.cpp
/workspace/Prototypes/pytorch3d/pytorch3d/csrc/point_mesh/point_mesh.cpp
/workspace/Prototypes/pytorch3d/pytorch3d/csrc/point_mesh/point_mesh_edge.cu
/workspace/Prototypes/pytorch3d/pytorch3d/csrc/point_mesh/point_mesh_face.cu
/workspace/Prototypes/pytorch3d/pytorch3d/csrc/rasterize_meshes/rasterize_meshes.cu
/workspace/Prototypes/pytorch3d/pytorch3d/csrc/rasterize_meshes/rasterize_meshes_cpu.cpp
/workspace/Prototypes/pytorch3d/pytorch3d/csrc/rasterize_points/rasterize_points.cu
pytorch3d_mcg.egg-info/PKG-INFO
pytorch3d_mcg.egg-info/SOURCES.txt
pytorch3d_mcg.egg-info/dependency_links.txt
pytorch3d_mcg.egg-info/requires.txt
pytorch3d_mcg.egg-info/top_level.txt