Metadata-Version: 2.1
Name: pytorch3d-mcg
Version: 0.2.5
Summary: PyTorch3D is FAIR's library of reusable components for deep Learning with 3D data. This is a customed version by MCG team
Home-page: https://github.com/pableeto/pytorch3d
Author: FAIR
License: UNKNOWN
Platform: UNKNOWN
Provides-Extra: dev
Provides-Extra: all
